jsonpaws/__init__.py
jsonpaws/content_generator.py
jsonpaws/json_processor.py
jsonpaws/prompt_generator.py
jsonpaws/schema_parser.py
jsonpaws/utils.py
json_paws-0.1.9.dist-info/LICENSE
json_paws-0.1.9.dist-info/METADATA
json_paws-0.1.9.dist-info/WHEEL
json_paws-0.1.9.dist-info/top_level.txt
json_paws-0.1.9.dist-info/RECORD
