Metadata-Version: 2.1
Name: json_paws
Version: 0.1.9
Summary: A library for generating structured JSON using GPT-4o.
Home-page: https://github.com/caspianmoon/jsonpaws
Author: Khazar Ayaz
Author-email: khazar.ayaz@personnoai.com
License: MIT
Classifier: Programming Language :: Python :: 3
Classifier: License :: OSI Approved :: MIT License
Classifier: Operating System :: OS Independent
Requires-Python: >=3.6
License-File: LICENSE
Requires-Dist: openai
